platon/__init__.py
platon/config.py
platon/constants.py
platon/db.py
platon/functions.py
platon/platon.py
platon/utils.py
cb_platon-1.7.dist-info/LICENSE
cb_platon-1.7.dist-info/METADATA
cb_platon-1.7.dist-info/WHEEL
cb_platon-1.7.dist-info/entry_points.txt
cb_platon-1.7.dist-info/top_level.txt
cb_platon-1.7.dist-info/RECORD
