Metadata-Version: 2.1
Name: cb-platon
Version: 1.7
Summary: Platon: identification and characterization of bacterial plasmid contigs from short-read draft assemblies.
Home-page: https://github.com/oschwengers/platon
Author: Oliver Schwengers
Author-email: oliver.schwengers@computational.bio.uni-giessen.de
License: GPLv3
Project-URL: Bug Reports, https://github.com/oschwengers/platon/issues
Project-URL: Source, https://github.com/oschwengers/platon
Keywords: bioinformatics,plasmids,wgs
Platform: UNKNOWN
Classifier: Operating System :: POSIX :: Linux
Classifier: Programming Language :: Python :: 3 :: Only
Classifier: Programming Language :: Python :: 3.8
Classifier: Programming Language :: Python :: 3.9
Classifier: Development Status :: 5 - Production/Stable
Classifier: License :: OSI Approved :: GNU General Public License v3 (GPLv3)
Classifier: Topic :: Scientific/Engineering :: Bio-Informatics
Classifier: Environment :: Console
Classifier: Intended Audience :: Science/Research
Classifier: Natural Language :: English
Requires-Python: >=3.8
Requires-Dist: biopython >=1.78
